AUTHORS.rst
CONTRIBUTING.rst
HISTORY.rst
LICENSE
MANIFEST.in
README.rst
setup.cfg
setup.py
api_data/__init__.py
api_data/api_data.py
api_data/census.py
api_data.egg-info/PKG-INFO
api_data.egg-info/SOURCES.txt
api_data.egg-info/dependency_links.txt
api_data.egg-info/not-zip-safe
api_data.egg-info/top_level.txt
docs/Makefile
docs/authors.rst
docs/conf.py
docs/contributing.rst
docs/history.rst
docs/index.rst
docs/installation.rst
docs/make.bat
docs/readme.rst
docs/usage.rst
tests/__init__.py
tests/test_api_data.py