Metadata-Version: 1.1
Name: api-data
Version: 0.1.0
Summary: API Data makes working with open data APIs easy.
Home-page: https://github.com/mikeasilva/api_data
Author: Michael Silva
Author-email: mike.a.silva@gmail.com
License: GNU General Public License v3
Keywords: api_data
Platform: UNKNOWN
Classifier: Development Status :: 2 - Pre-Alpha
Classifier: Intended Audience :: Developers
Classifier: License :: OSI Approved :: GNU General Public License v3 (GPLv3)
Classifier: Natural Language :: English
Classifier: Programming Language :: Python :: 2
Classifier: Programming Language :: Python :: 2.7
Classifier: Programming Language :: Python :: 3
Classifier: Programming Language :: Python :: 3.4
Classifier: Programming Language :: Python :: 3.5
Classifier: Programming Language :: Python :: 3.6
